cotegen/__init__.py
cotegen/__main__.py
cotegen/branch_tree.py
cotegen/context.py
cotegen/function_def.py
cotegen/kill.py
cotegen/my_random.py
cotegen/task.py
cotegen/test.py
cotegen/_types/__init__.py
cotegen/_types/integer.py
cotegen/_types/integersequence.py
cotegen/ast_utils/__init__.py
cotegen/ast_utils/tree_walk.py
cotegen/constraints/__init__.py
cotegen/constraints/compare_integers.py
cotegen/constraints/compare_list_to_element.py
cotegen/exceptions/__init__.py
cotegen/localsearch/__init__.py
cotegen/localsearch/avm.py
cotegen/localsearch/distance_functions.py
cotegen/localsearch/fitnesscalc.py
cotegen/localsearch/mutation_distance_functions.py
cotegen/localsearch/trace.py
cotegen/mutation/__init__.py
cotegen/mutation/generator.py
cotegen/mutation/mutator.py
cotegen/mutation/operators.py
cotegen-1.1.dist-info/LICENSE
cotegen-1.1.dist-info/METADATA
cotegen-1.1.dist-info/WHEEL
cotegen-1.1.dist-info/top_level.txt
cotegen-1.1.dist-info/RECORD
